{
  "image": "page_21.webp",
  "w": 1633,
  "h": 2046,
  "page": "19",
  "topic": "Flam Beats",
  "items": [
    {
      "title": "#73",
      "bbox": {
        "x": 18,
        "y": 43,
        "w": 826,
        "h": 154
      }
    },
    {
      "title": "#74",
      "bbox": {
        "x": 48,
        "y": 209,
        "w": 796,
        "h": 154
      }
    },
    {
      "title": "#75",
      "bbox": {
        "x": 48,
        "y": 376,
        "w": 796,
        "h": 154
      }
    },
    {
      "title": "#76",
      "bbox": {
        "x": 48,
        "y": 543,
        "w": 796,
        "h": 154
      }
    },
    {
      "title": "#77",
      "bbox": {
        "x": 48,
        "y": 710,
        "w": 796,
        "h": 154
      }
    },
    {
      "title": "#78",
      "bbox": {
        "x": 48,
        "y": 877,
        "w": 796,
        "h": 154
      }
    },
    {
      "title": "#79",
      "bbox": {
        "x": 48,
        "y": 1044,
        "w": 796,
        "h": 154
      }
    },
    {
      "title": "#80",
      "bbox": {
        "x": 48,
        "y": 1210,
        "w": 796,
        "h": 154
      }
    },
    {
      "title": "#81",
      "bbox": {
        "x": 48,
        "y": 1377,
        "w": 796,
        "h": 154
      }
    },
    {
      "title": "#82",
      "bbox": {
        "x": 48,
        "y": 1544,
        "w": 796,
        "h": 154
      }
    },
    {
      "title": "#83",
      "bbox": {
        "x": 48,
        "y": 1711,
        "w": 796,
        "h": 154
      }
    },
    {
      "title": "#84",
      "bbox": {
        "x": 48,
        "y": 1880,
        "w": 796,
        "h": 154
      }
    },
    {
      "title": "#85",
      "bbox": {
        "x": 854,
        "y": 43,
        "w": 752,
        "h": 154
      }
    },
    {
      "title": "#86",
      "bbox": {
        "x": 854,
        "y": 209,
        "w": 752,
        "h": 154
      }
    },
    {
      "title": "#87",
      "bbox": {
        "x": 854,
        "y": 376,
        "w": 752,
        "h": 154
      }
    },
    {
      "title": "#88",
      "bbox": {
        "x": 854,
        "y": 543,
        "w": 752,
        "h": 154
      }
    },
    {
      "title": "#89",
      "bbox": {
        "x": 854,
        "y": 710,
        "w": 752,
        "h": 154
      }
    },
    {
      "title": "#90",
      "bbox": {
        "x": 854,
        "y": 877,
        "w": 752,
        "h": 154
      }
    },
    {
      "title": "#91",
      "bbox": {
        "x": 854,
        "y": 1044,
        "w": 752,
        "h": 154
      }
    },
    {
      "title": "#92",
      "bbox": {
        "x": 854,
        "y": 1210,
        "w": 752,
        "h": 154
      }
    },
    {
      "title": "#93",
      "bbox": {
        "x": 854,
        "y": 1377,
        "w": 752,
        "h": 154
      }
    },
    {
      "title": "#94",
      "bbox": {
        "x": 854,
        "y": 1544,
        "w": 752,
        "h": 154
      }
    },
    {
      "title": "#95",
      "bbox": {
        "x": 854,
        "y": 1711,
        "w": 752,
        "h": 154
      }
    },
    {
      "title": "#96",
      "bbox": {
        "x": 854,
        "y": 1880,
        "w": 752,
        "h": 154
      }
    }
  ]
}