{
  "image": "page_36.webp",
  "w": 1667,
  "h": 2280,
  "page": "34",
  "topic": "Flam Triplets and Dotted Notes",
  "items": [
    {
      "title": "#1",
      "bbox": {
        "x": 54,
        "y": 188,
        "w": 826,
        "h": 153
      }
    },
    {
      "title": "#2",
      "bbox": {
        "x": 100,
        "y": 342,
        "w": 778,
        "h": 154
      }
    },
    {
      "title": "#3",
      "bbox": {
        "x": 101,
        "y": 498,
        "w": 777,
        "h": 152
      }
    },
    {
      "title": "#4",
      "bbox": {
        "x": 100,
        "y": 652,
        "w": 778,
        "h": 153
      }
    },
    {
      "title": "#5",
      "bbox": {
        "x": 98,
        "y": 807,
        "w": 779,
        "h": 154
      }
    },
    {
      "title": "#6",
      "bbox": {
        "x": 95,
        "y": 963,
        "w": 783,
        "h": 152
      }
    },
    {
      "title": "#7",
      "bbox": {
        "x": 888,
        "y": 188,
        "w": 751,
        "h": 153
      }
    },
    {
      "title": "#8",
      "bbox": {
        "x": 888,
        "y": 343,
        "w": 751,
        "h": 153
      }
    },
    {
      "title": "#9",
      "bbox": {
        "x": 888,
        "y": 498,
        "w": 751,
        "h": 152
      }
    },
    {
      "title": "#10",
      "bbox": {
        "x": 888,
        "y": 652,
        "w": 751,
        "h": 153
      }
    },
    {
      "title": "#11",
      "bbox": {
        "x": 888,
        "y": 807,
        "w": 751,
        "h": 154
      }
    },
    {
      "title": "#12",
      "bbox": {
        "x": 888,
        "y": 963,
        "w": 751,
        "h": 152
      }
    },
    {
      "title": "#13",
      "bbox": {
        "x": 86,
        "y": 1218,
        "w": 1553,
        "h": 155
      }
    },
    {
      "title": "#14",
      "bbox": {
        "x": 87,
        "y": 1376,
        "w": 1552,
        "h": 153
      }
    },
    {
      "title": "#15",
      "bbox": {
        "x": 87,
        "y": 1532,
        "w": 1552,
        "h": 154
      }
    },
    {
      "title": "#16",
      "bbox": {
        "x": 87,
        "y": 1689,
        "w": 1552,
        "h": 153
      }
    },
    {
      "title": "#17",
      "bbox": {
        "x": 87,
        "y": 1844,
        "w": 1552,
        "h": 154
      }
    },
    {
      "title": "#18",
      "bbox": {
        "x": 87,
        "y": 2001,
        "w": 1552,
        "h": 153
      }
    }
  ]
}